README.md
setup.py
bb_database.egg-info/PKG-INFO
bb_database.egg-info/SOURCES.txt
bb_database.egg-info/dependency_links.txt
bb_database.egg-info/requires.txt
bb_database.egg-info/top_level.txt
common/__init__.py
common/config.py
common/customTypes.py
models/__init__.py
models/e_comm_models.py